splitbbox/__init__.py
splitbbox/_nbdev.py
splitbbox/core.py
splitbbox-0.0.1.dist-info/LICENSE
splitbbox-0.0.1.dist-info/METADATA
splitbbox-0.0.1.dist-info/WHEEL
splitbbox-0.0.1.dist-info/entry_points.txt
splitbbox-0.0.1.dist-info/top_level.txt
splitbbox-0.0.1.dist-info/RECORD
